[
	{
		"action": "variable",
		"target": "player",
		"args": {
			"name": "disable_controls",
			"value": true
		}
	},
	{
		"action": "show_dialogue",
		"wait": "advance_dialogue",
		"args": {
			"name": "3R",
			"mood": "normal",
			"text": "Please keep your eyes peeled for anything unusual, Captain!",
			"action": "interact",
			"direction": "right",
			"time": 0
		}
	},
	{
		"action": "show_dialogue",
		"wait": "advance_dialogue",
		"args": {
			"name": "martin",
			"mood": "angry",
			"text": "Hey, I know why I am here. Please stop behaving like a stupid machine!",
			"action": "interact",
			"direction": "left",
			"time": 0
		}
	},
	{
		"action": "show_dialogue",
		"wait": "advance_dialogue",
		"args": {
			"name": "3R",
			"mood": "normal",
			"text": "Ouchie...",
			"action": "interact",
			"direction": "right",
			"time": 0
		}
	},
	{
		"action": "timer",
		"wait": 0.25
	},
	{
		"action": "variable",
		"target": "player",
		"args": {
			"name": "disable_controls",
			"value": false
		}
	},
]
